synthetic_datasets/NoiseCircle.py
synthetic_datasets/SyntheticDataset.py
synthetic_datasets/__init__.py
synthetic_datasets-0.1.11.dist-info/METADATA
synthetic_datasets-0.1.11.dist-info/RECORD
synthetic_datasets-0.1.11.dist-info/WHEEL
synthetic_datasets-0.1.11.dist-info/top_level.txt
