Metadata-Version: 2.1
Name: synthetic-datasets
Version: 0.1.11
Summary: synthetic datasets for benchmarking AI and machine learning
Home-page: https://github.com/synthetic-datasets/synthetic-datasets
Author: Dave MacDonald
Author-email: dave@torontoai.org
License: UNKNOWN
Platform: UNKNOWN
Classifier: Programming Language :: Python :: 3
Classifier: License :: OSI Approved :: MIT License
Classifier: Operating System :: OS Independent
Requires-Dist: numpy
